bsod/__init__.py
bsod/main.py
bsod/utils.py
bsod/assets/audio.mp3
bsod/assets/image.png
bsod-0.1.4.dist-info/licenses/LICENSE
bsod-0.1.4.dist-info/METADATA
bsod-0.1.4.dist-info/WHEEL
bsod-0.1.4.dist-info/entry_points.txt
bsod-0.1.4.dist-info/top_level.txt
bsod-0.1.4.dist-info/RECORD
