Metadata-Version: 2.4
Name: bsod
Version: 0.1.4
Summary: Blue Screen of Death
Home-page: https://github.com/arpy8/bsod
Author: arpy8
Author-email: arpitsengar99@gmail.com
License: MIT
Classifier: Programming Language :: Python :: 3
Classifier: License :: OSI Approved :: MIT License
Classifier: Operating System :: OS Independent
License-File: LICENSE
Requires-Dist: pygame
Requires-Dist: keyboard
Requires-Dist: pywin32
Requires-Dist: pyautogui
Requires-Dist: setuptools==66.1.1
Dynamic: author
Dynamic: author-email
Dynamic: classifier
Dynamic: description
Dynamic: description-content-type
Dynamic: home-page
Dynamic: license
Dynamic: license-file
Dynamic: requires-dist
Dynamic: summary
